pyispace/__init__.py
pyispace/__main__.py
pyispace/cli.py
pyispace/example.py
pyispace/pilot.py
pyispace/preprocessing.py
pyispace/trace.py
pyispace/train.py
pyispace/utils.py
pyispace-0.3.7.dist-info/entry_points.txt
pyispace-0.3.7.dist-info/WHEEL
pyispace-0.3.7.dist-info/METADATA
pyispace-0.3.7.dist-info/RECORD
