Metadata-Version: 2.1
Name: pyispace
Version: 0.3.7
Summary: Instance Space Analysis Python package
Author-email: Pedro Paiva <paiva@ita.br>
Requires-Python: >=3.7
Classifier: Development Status :: 5 - Production/Stable
Classifier: Programming Language :: Python :: 3
Classifier: License :: OSI Approved :: MIT License
Classifier: Operating System :: OS Independent
Classifier: Topic :: Scientific/Engineering :: Artificial Intelligence
Classifier: Intended Audience :: Science/Research
Requires-Dist: numpy>=1.18.5
Requires-Dist: scipy>=1.9.0
Requires-Dist: scikit-learn>=0.23.1
Requires-Dist: shapely~=1.8.0
Requires-Dist: pandas>=1.1
Requires-Dist: alphashape>=1.3.1
Requires-Dist: joblib>=1.3.0
Project-URL: repository, https://gitlab.com/ita-ml/pyispace
